retry_deco/__init__.py
retry_deco/retry.py
retry_deco-0.0.3.dist-info/licenses/LICENSE.txt
retry_deco-0.0.3.dist-info/METADATA
retry_deco-0.0.3.dist-info/WHEEL
retry_deco-0.0.3.dist-info/top_level.txt
retry_deco-0.0.3.dist-info/RECORD
