Metadata-Version: 2.4
Name: retry-deco
Version: 0.0.3
Summary: Retry decorator for both synchronous and asynchronous functions.
Author: Laur
Maintainer: Laur
License-Expression: MIT
Project-URL: homepage, https://github.com/haridusministeerium/retry-deco
Project-URL: issues, https://github.com/haridusministeerium/retry-deco/issues
Project-URL: changelog, https://github.com/haridusministeerium/retry-deco/blob/master/CHANGELOG.md
Keywords: decorator,retry,async-retry,retry-deco
Classifier: Development Status :: 5 - Production/Stable
Classifier: Intended Audience :: Developers
Classifier: Topic :: Software Development :: Libraries
Classifier: Programming Language :: Python :: 3
Classifier: Operating System :: OS Independent
Requires-Python: >=3.11
License-File: LICENSE.txt
Provides-Extra: dev
Requires-Dist: pytest; extra == "dev"
Requires-Dist: pytest-asyncio; extra == "dev"
Requires-Dist: pytest-cov; extra == "dev"
Requires-Dist: ruff; extra == "dev"
Requires-Dist: ty; extra == "dev"
Requires-Dist: ipdb; extra == "dev"
Dynamic: license-file
